{
    "clusters": [
        {
            "nodes": [
                {
                    "node": {
                        "hostnames": {
                            "manage": [
                                "gluster1-a"
                            ],
                            "storage": [
                                "10.152.0.2"
                            ]
                        },
                        "zone": 1
                    },
                    "devices": [
                        "/dev/sdb"
                    ]
                },
                {
                    "node": {
                        "hostnames": {
                            "manage": [
                                "gluster1-b"
                            ],
                            "storage": [
                                "10.152.0.3"
                            ]
                        },
                        "zone": 2
                    },
                    "devices": [
                        "/dev/sdb"
                    ]
                },
                {
                    "node": {
                        "hostnames": {
                            "manage": [
                                "gluster1-c"
                            ],
                            "storage": [
                                "10.152.0.4"
                            ]
                        },
                        "zone": 3
                    },
                    "devices": [
                        "/dev/sdb"
                    ]
                }
            ]
        }
    ]
}
